momotor/bundles/__init__.py
momotor/bundles/base.py
momotor/bundles/config.py
momotor/bundles/const.py
momotor/bundles/exception.py
momotor/bundles/product.py
momotor/bundles/recipe.py
momotor/bundles/results.py
momotor/bundles/test.py
momotor/bundles/testresult.py
momotor/bundles/binding/__init__.py
momotor/bundles/binding/momotor_1_0.py
momotor/bundles/binding/xml.py
momotor/bundles/elements/__init__.py
momotor/bundles/elements/base.py
momotor/bundles/elements/checklets.py
momotor/bundles/elements/content.py
momotor/bundles/elements/files.py
momotor/bundles/elements/meta.py
momotor/bundles/elements/options.py
momotor/bundles/elements/properties.py
momotor/bundles/elements/refs.py
momotor/bundles/elements/resources.py
momotor/bundles/elements/result.py
momotor/bundles/elements/results.py
momotor/bundles/elements/steps.py
momotor/bundles/elements/wildcard.py
momotor/bundles/mixins/__init__.py
momotor/bundles/mixins/attachments.py
momotor/bundles/mixins/id.py
momotor/bundles/mixins/name.py
momotor/bundles/parsers/__init__.py
momotor/bundles/parsers/config.py
momotor/bundles/parsers/xml.py
momotor/bundles/parsers/handlers/__init__.py
momotor/bundles/parsers/handlers/exceptions.py
momotor/bundles/parsers/handlers/lxml.py
momotor/bundles/parsers/handlers/xml.py
momotor/bundles/schema/momotor-1.0.xsd
momotor/bundles/schema/xml.xsd
momotor/bundles/serializers/__init__.py
momotor/bundles/serializers/config.py
momotor/bundles/serializers/xml.py
momotor/bundles/serializers/writers/__init__.py
momotor/bundles/serializers/writers/lxml.py
momotor/bundles/serializers/writers/xml.py
momotor/bundles/typing/__init__.py
momotor/bundles/typing/element.py
momotor/bundles/utils/__init__.py
momotor/bundles/utils/arguments.py
momotor/bundles/utils/ascii.py
momotor/bundles/utils/assertion.py
momotor/bundles/utils/boolean.py
momotor/bundles/utils/detect.py
momotor/bundles/utils/domain.py
momotor/bundles/utils/encoding.py
momotor/bundles/utils/filters.py
momotor/bundles/utils/grouping.py
momotor_bundles-8.1.1.dist-info/LICENSE.txt
momotor_bundles-8.1.1.dist-info/METADATA
momotor_bundles-8.1.1.dist-info/WHEEL
momotor_bundles-8.1.1.dist-info/top_level.txt
momotor_bundles-8.1.1.dist-info/RECORD
