Metadata-Version: 2.1
Name: momotor-bundles
Version: 8.1.1
Summary: Momotor bundle reader, writer, tools
Author-email: Erik Scheffers <e.t.j.scheffers@tue.nl>
License: GNU Lesser General Public License v3 (LGPLv3)
Project-URL: Homepage, https://momotor.org
Project-URL: Documentation, https://momotor.org/doc/engine/momotor-bundles/
Project-URL: Repository, https://gitlab.tue.nl/momotor/engine-py3/momotor-bundles/
Project-URL: Tracker, https://gitlab.tue.nl/momotor/engine-py3/momotor-bundles/issues
Classifier: Development Status :: 5 - Production/Stable
Classifier: Intended Audience :: Developers
Classifier: Programming Language :: Python
Classifier: Programming Language :: Python :: 3.9
Classifier: Programming Language :: Python :: 3.10
Classifier: Programming Language :: Python :: 3.11
Classifier: Programming Language :: Python :: 3.12
Classifier: Programming Language :: Python :: 3 :: Only
Requires-Python: >=3.9
License-File: LICENSE.txt
Requires-Dist: pathvalidate
Requires-Dist: xsdata <24.8,>=24.7
Requires-Dist: typing-extensions ; python_version < "3.11"
Provides-Extra: build
Requires-Dist: momotor-bundles[dev] ; extra == 'build'
Requires-Dist: setuptools ; extra == 'build'
Requires-Dist: setuptools-scm ; extra == 'build'
Requires-Dist: build[virtualenv] ; extra == 'build'
Requires-Dist: python-semantic-release ~=9.0 ; extra == 'build'
Provides-Extra: dev
Requires-Dist: momotor-bundles[docs,lxml] ; extra == 'dev'
Requires-Dist: docutils-stubs ; extra == 'dev'
Requires-Dist: xsdata[cli] <24.8,>=24.7 ; extra == 'dev'
Provides-Extra: docs
Requires-Dist: momotor-bundles[test] ; extra == 'docs'
Requires-Dist: Sphinx ; extra == 'docs'
Requires-Dist: sphinx-autodoc-typehints !=1.14.0 ; extra == 'docs'
Requires-Dist: furo ; extra == 'docs'
Provides-Extra: lxml
Requires-Dist: xsdata[lxml] <24.8,>=24.7 ; extra == 'lxml'
Provides-Extra: test
Requires-Dist: momotor-bundles[lxml] ; extra == 'test'
Requires-Dist: pytest ~=8.1 ; extra == 'test'
Requires-Dist: pytest-cov ; extra == 'test'
Requires-Dist: pytest-doctestplus ; extra == 'test'
Requires-Dist: xmljson ; extra == 'test'
